Workbook
Name Slicer_Customer_Name: #N/A
Name Slicer_Payment_Mode: #N/A

Sheet Sales_Data
A5: Order_ID | B5: Order_Date | C5: Customer_Name | D5: Region | E5: Product | F5: Category | G5: Quantity | H5: Unit_Price | I5: Total_Sales | J5: Payment_Mode
A6: ORD0001 | B6: 45777 | C6: Pooja | D6: South | E6: Laptop | F6: Electronics | G6: 3 | H6: 44856 | I6: 134568 | J6: UPI
A7: ORD0002 | B7: 45752 | C7: Pooja | D7: East | E7: Laptop | F7: Accessories | G7: 5 | H7: 12332 | I7: 61660 | J7: Cash
A8: ORD0003 | B8: 45772 | C8: Diya | D8: South | E8: Mobile | F8: Electronics | G8: 2 | H8: 42847 | I8: 85694 | J8: Cash
A9: ORD0004 | B9: 45788 | C9: Meera | D9: North | E9: Mobile | F9: Electronics | G9: 1 | H9: 35731 | I9: 35731 | J9: UPI
A10: ORD0005 | B10: 45830 | C10: Pooja | D10: North | E10: Tablet | F10: Electronics | G10: 1 | H10: 43475 | I10: 43475 | J10: Debit Card
A11: ORD0006 | B11: 45669 | C11: Diya | D11: East | E11: Smartwatch | F11: Accessories | G11: 2 | H11: 2624 | I11: 5248 | J11: Credit Card
A12: ORD0007 | B12: 45828 | C12: Meera | D12: North | E12: Mobile | F12: Electronics | G12: 2 | H12: 17348 | I12: 34696 | J12: Credit Card
A13: ORD0008 | B13: 45682 | C13: Pooja | D13: North | E13: Laptop | F13: Accessories | G13: 5 | H13: 6996 | I13: 34980 | J13: Credit Card
A14: ORD0009 | B14: 45669 | C14: Meera | D14: North | E14: Mobile | F14: Accessories | G14: 1 | H14: 18386 | I14: 18386 | J14: Debit Card
A15: ORD0010 | B15: 45787 | C15: Diya | D15: West | E15: Smartwatch | F15: Accessories | G15: 4 | H15: 32867 | I15: 131468 | J15: Cash
A16: ORD0011 | B16: 45676 | C16: Meera | D16: North | E16: Tablet | F16: Electronics | G16: 2 | H16: 41604 | I16: 83208 | J16: Cash
A17: ORD0012 | B17: 45715 | C17: Kiran | D17: North | E17: Smartwatch | F17: Accessories | G17: 2 | H17: 28140 | I17: 56280 | J17: Debit Card
... A105: ORD0100 | B105: 45780 | C105: Rohan | D105: East | E105: Mobile | F105: Accessories | G105: 5 | H105: 28670 | I105: 143350 | J105: Cash

Sheet pivot table
I1: Monthly sales
A2: Sales by region | I2: month | J2: Sum of Total_Sales
A3: Region | B3: Total_Sales sum | C3: Sum of Quantity | I3: Jan | J3: 184924
A4: East | B4: 842736 | C4: 31 | I4: Feb | J4: 195994
A5: North | B5: 170185 | C5: 7 | I5: Mar | J5: 630589
A6: South | B6: 530033 | C6: 17 | I6: Apr | J6: 183118
A7: West | B7: 440755 | C7: 13 | I7: May | J7: 453798
A8: Grand Total | B8: 1983709 | C8: 68 | I8: Jun | J8: 335286
I9: Grand Total | J9: 1983709
A10: Category | B10: (All)
A11: Sales by Product
A12: Product | B12: Sum of Quantity | C12: Total_Sales by product | E12: max product sold
A13: Tablet | B13: 23 | C13: 568197
A14: Headphones | B14: 14 | C14: 487348 | E14: =MAX(B13:B17) -> 23
A15: Laptop | B15: 16 | C15: 435351
A16: Smartwatch | B16: 12 | C16: 407520
A17: Mobile | B17: 3 | C17: 85293
A18: Grand Total | B18: 68 | C18: 1983709
A26: customer | B26: Sum of Quantity
A27: Rohan | B27: 15
A28: Meera | B28: 15
A29: Vikram | B29: 10
A30: Kiran | B30: 10
A31: Ananya | B31: 10
A32: Pooja | B32: 8
A33: Grand Total | B33: 68

Sheet Sales Dashboard
E2: Sales Dashboard
D15: Region | E15: Total sales | F15: Quantity sold | L15: Product | M15: Sum of Quantity | N15: Total_Sales by product
D16: ='pivot table'!A4 -> East | E16: ='pivot table'!B4 -> 842736 | F16: ='pivot table'!C4 -> 31 | L16: ='pivot table'!A13 -> Tablet | M16: ='pivot table'!B13 -> 23 | N16: ='pivot table'!C13 -> 568197
D17: ='pivot table'!A5 -> North | E17: ='pivot table'!B5 -> 170185 | F17: ='pivot table'!C5 -> 7 | L17: ='pivot table'!A14 -> Headphones | M17: ='pivot table'!B14 -> 14 | N17: ='pivot table'!C14 -> 487348
D18: ='pivot table'!A6 -> South | E18: ='pivot table'!B6 -> 530033 | F18: ='pivot table'!C6 -> 17 | L18: ='pivot table'!A15 -> Laptop | M18: ='pivot table'!B15 -> 16 | N18: ='pivot table'!C15 -> 435351
D19: ='pivot table'!A7 -> West | E19: ='pivot table'!B7 -> 440755 | F19: ='pivot table'!C7 -> 13 | L19: ='pivot table'!A16 -> Smartwatch | M19: ='pivot table'!B16 -> 12 | N19: ='pivot table'!C16 -> 407520
D20: ='pivot table'!A8 -> Grand Total | E20: ='pivot table'!B8 -> 1983709 | F20: ='pivot table'!C8 -> 68 | L20: ='pivot table'!A17 -> Mobile | M20: ='pivot table'!B17 -> 3 | N20: ='pivot table'!C17 -> 85293
L21: ='pivot table'!A18 -> Grand Total | M21: ='pivot table'!B18 -> 68 | N21: ='pivot table'!C18 -> 1983709

Sheet backup data
A5: Order_ID | B5: Order_Date | C5: Customer_Name | D5: Region | E5: Product | F5: Category | G5: Quantity | H5: Unit_Price | I5: Total_Sales | J5: Payment_Mode
A6: ORD0001 | B6: 45777 | C6: Pooja | D6: South | E6: Laptop | F6: Electronics | G6: 3 | H6: 44856 | I6: 134568 | J6: UPI
A7: ORD0002 | B7: 45752 | C7: Pooja | D7: East | E7: Laptop | F7: Accessories | G7: 5 | H7: 12332 | I7: 61660 | J7: Cash
A8: ORD0003 | B8: 45772 | C8: Diya | D8: South | E8: Mobile | F8: Electronics | G8: 2 | H8: 42847 | I8: 85694 | J8: Cash
A9: ORD0004 | B9: 45788 | C9: Meera | D9: North | E9: Mobile | F9: Electronics | G9: 1 | H9: 35731 | I9: 35731 | J9: UPI
A10: ORD0005 | B10: 45830 | C10: Pooja | D10: North | E10: Tablet | F10: Electronics | G10: 1 | H10: 43475 | I10: 43475 | J10: Debit Card
A11: ORD0006 | B11: 45669 | C11: Diya | D11: East | E11: Smartwatch | F11: Accessories | G11: 2 | H11: 2624 | I11: 5248 | J11: Credit Card
A12: ORD0007 | B12: 45828 | C12: Meera | D12: North | E12: Mobile | F12: Electronics | G12: 2 | H12: 17348 | I12: 34696 | J12: Credit Card
A13: ORD0008 | B13: 45682 | C13: Pooja | D13: North | E13: Laptop | F13: Accessories | G13: 5 | H13: 6996 | I13: 34980 | J13: Credit Card
A14: ORD0009 | B14: 45669 | C14: Meera | D14: North | E14: Mobile | F14: Accessories | G14: 1 | H14: 18386 | I14: 18386 | J14: Debit Card
A15: ORD0010 | B15: 45787 | C15: Diya | D15: West | E15: Smartwatch | F15: Accessories | G15: 4 | H15: 32867 | I15: 131468 | J15: Cash
A16: ORD0011 | B16: 45676 | C16: Meera | D16: North | E16: Tablet | F16: Electronics | G16: 2 | H16: 41604 | I16: 83208 | J16: Cash
A17: ORD0012 | B17: 45715 | C17: Kiran | D17: North | E17: Smartwatch | F17: Accessories | G17: 2 | H17: 28140 | I17: 56280 | J17: Debit Card
... A105: ORD0100 | B105: 45780 | C105: Rohan | D105: East | E105: Mobile | F105: Accessories | G105: 5 | H105: 28670 | I105: 143350 | J105: Cash
